switchmate/__init__.py
PySwitchmate-0.5.1.dist-info/LICENSE
PySwitchmate-0.5.1.dist-info/METADATA
PySwitchmate-0.5.1.dist-info/WHEEL
PySwitchmate-0.5.1.dist-info/top_level.txt
PySwitchmate-0.5.1.dist-info/RECORD
