Metadata-Version: 2.1
Name: PySwitchmate
Version: 0.5.1
Summary: A library to communicate with Switchmate
Home-page: https://github.com/Danielhiversen/pySwitchmate/
Author: Daniel Hjelseth Hoyer
License: UNKNOWN
Platform: UNKNOWN
Classifier: Development Status :: 3 - Alpha
Classifier: Environment :: Other Environment
Classifier: Intended Audience :: Developers
Classifier: Operating System :: OS Independent
Classifier: Programming Language :: Python
Classifier: Topic :: Home Automation
Classifier: Topic :: Software Development :: Libraries :: Python Modules
License-File: LICENSE
